README.md
setup.py
tidygithub.py
tidygithub.egg-info/PKG-INFO
tidygithub.egg-info/SOURCES.txt
tidygithub.egg-info/dependency_links.txt
tidygithub.egg-info/requires.txt
tidygithub.egg-info/top_level.txt