Metadata-Version: 1.0
Name: tidygithub
Version: 0.0.1
Summary: tidy github API wrapping PyGithub
Home-page: https://github.com/machow/tidygithub
Author: Michael Chow
Author-email: mc_al_github@fastmail.com
License: UNKNOWN
Platform: UNKNOWN
